<?xml version="1.0" encoding="utf-8" ?>
<dwsync>
<file name="Logo.png" server="192.168.0.32//var/www/Lwala/" local="129865566430000000" remote="129865566430000000" Dst="0" />
<file name="tkhpadlock.png" server="192.168.0.32//var/www/Lwala/" local="129865566430000000" remote="129865566430000000" Dst="0" />
<file name="LwalaName.gif" server="192.168.0.32//var/www/Lwala/" local="129865566430000000" remote="129865566430000000" Dst="0" />
<file name="bg.jpg" server="192.168.0.32//var/www/Lwala/" local="129865566430000000" remote="129865566430000000" Dst="0" />
<file name="close.png" server="192.168.0.32//var/www/Lwala/" local="129865566430000000" remote="129865566430000000" Dst="0" />
<file name="Logo.png" server="192.168.0.32//var/www/Lwala/" local="129865566430000000" remote="129865566430000000" Dst="0" />
<file name="padlock.png" server="192.168.0.32//var/www/Lwala/" local="129865566430000000" remote="129865566430000000" Dst="0" />
<file name="form_top.jpg" server="192.168.0.32//var/www/Lwala/" local="129865566430000000" remote="129865566430000000" Dst="0" />
<file name="Logo.png" server="192.168.0.32//var/www/Lwala/" local="129865566430000000" remote="129865566430000000" Dst="0" />
<file name="folder_icon.png" server="192.168.0.32//var/www/Lwala/" local="129865566430000000" remote="129865566430000000" Dst="0" />
<file name="loading.gif" server="192.168.0.32//var/www/Lwala/" local="129865566430000000" remote="129865566430000000" Dst="0" />
<file name="padlock2.png" server="192.168.0.32//var/www/Lwala/" local="129865566430000000" remote="129865566430000000" Dst="0" />
<file name="LwalaName.png" server="192.168.0.32//var/www/Lwala/" local="129865566430000000" remote="129865566430000000" Dst="0" />
<file name="loginbg.png" server="192.168.0.32//var/www/Lwala/" local="129865566430000000" remote="129865566430000000" Dst="0" />
</dwsync>